gui.py
EasyTkinter-1.1.0.dist-info/DESCRIPTION.rst
EasyTkinter-1.1.0.dist-info/METADATA
EasyTkinter-1.1.0.dist-info/RECORD
EasyTkinter-1.1.0.dist-info/WHEEL
EasyTkinter-1.1.0.dist-info/metadata.json
EasyTkinter-1.1.0.dist-info/top_level.txt
