Metadata-Version: 1.1
Name: EasyTkinter
Version: 1.1.0
Summary: A module to greatly simplify tkinter applications.
Home-page: UNKNOWN
Author: Joe Bell
Author-email: joe@jb-labs.uk
License: MIT
Keywords: tkinter gui easy wrapper
Platform: UNKNOWN
Classifier: Development Status :: 5 - Production/Stable
Classifier: Intended Audience :: Developers
Classifier: Topic :: Desktop Environment
Classifier: Topic :: Software Development :: Libraries
Classifier: Natural Language :: English
Classifier: License :: OSI Approved :: MIT License
Classifier: Programming Language :: Python
